aws_utilities/aws_switch.py
aws_utilities/pending_stack_resources.py
aws_utilities/tail_cloudwatch_logs.py
aws_utilities/tail_stack_events.py
aws_utilities/wait_for_stack_complete.py
aws_utilities/watch_resource.py
aws_utilities-1.3.1.dist-info/entry_points.txt
aws_utilities-1.3.1.dist-info/WHEEL
aws_utilities-1.3.1.dist-info/METADATA
aws_utilities-1.3.1.dist-info/RECORD
