Metadata-Version: 2.1
Name: aws-utilities
Version: 1.3.1
Summary: Utilities for use with aws.
Home-page: https://github.com/reversefold/aws-utilities
License: MIT
Author: Justin Patrin
Author-email: papercrane@reversefold.com
Requires-Python: >=3.6,<4.0
Classifier: License :: OSI Approved :: MIT License
Classifier: Programming Language :: Python :: 3
Classifier: Programming Language :: Python :: 3.6
Classifier: Programming Language :: Python :: 3.7
Requires-Dist: ansiwrap (>=0.8.4,<0.9.0)
Requires-Dist: boto3 (>=1.9,<2.0)
Requires-Dist: colorama (>=0.4.1,<0.5.0)
Requires-Dist: docopt (>=0.6.2,<0.7.0)
Requires-Dist: ec2-metadata (>=2.0,<3.0)
Requires-Dist: eventlet (>=0.24.1,<0.25.0)
Requires-Dist: tenacity (>=5.0,<6.0)
Requires-Dist: urllib3 (>=1.24,<1.25)
Project-URL: Repository, https://github.com/reversefold/aws-utilities.git
